cloud_scanner/__init__.py
cloud_scanner/settings.py
cloud_scanner/version.py
cloud_scanner/config/__init__.py
cloud_scanner/config/configuration.py
cloud_scanner/config/process_config.py
cloud_scanner/contracts/__init__.py
cloud_scanner/contracts/account_service.py
cloud_scanner/contracts/account_service_factory.py
cloud_scanner/contracts/cloud_config_generator.py
cloud_scanner/contracts/cloud_config_reader.py
cloud_scanner/contracts/queue.py
cloud_scanner/contracts/queue_factory.py
cloud_scanner/contracts/resource.py
cloud_scanner/contracts/resource_service.py
cloud_scanner/contracts/resource_service_factory.py
cloud_scanner/contracts/resource_storage_factory.py
cloud_scanner/contracts/rule.py
cloud_scanner/contracts/rule_factory.py
cloud_scanner/contracts/storage_container.py
cloud_scanner/contracts/storage_container_factory.py
cloud_scanner/contracts/table_storage.py
cloud_scanner/contracts/tag_update_rule.py
cloud_scanner/helpers/__init__.py
cloud_scanner/helpers/entry_storage.py
cloud_scanner/helpers/functions.py
cloud_scanner/rules/__init__.py
cloud_scanner/rules/example_rules.py
cloud_scanner/services/__init__.py
cloud_scanner/services/resource_scanner.py
cloud_scanner/services/resource_storage.py
cloud_scanner/services/resource_tagger.py
cloud_scanner/services/task_scheduler.py
cloud_scanner/simulators/__init__.py
cloud_scanner/simulators/account_service_simulator.py
cloud_scanner/simulators/container_storage_simulator.py
cloud_scanner/simulators/queue_simulator.py
cloud_scanner/simulators/resource_service_simulator.py
cloud_scanner/simulators/table_storage_simulator.py
tests/__init__.py
tests/test_account_service_factory.py
tests/test_config_generator.py
tests/test_example_rules.py
tests/test_integration.py
tests/test_resource_scanner.py
tests/test_resource_service_factory.py
tests/test_resource_storage.py
tests/test_resource_storage_factory.py
tests/test_resource_tagger.py
tests/test_rule_factory.py
tests/test_scheduler.py
cloud_scanner-0.1.3.dist-info/LICENSE
cloud_scanner-0.1.3.dist-info/METADATA
cloud_scanner-0.1.3.dist-info/WHEEL
cloud_scanner-0.1.3.dist-info/top_level.txt
cloud_scanner-0.1.3.dist-info/RECORD
