Metadata-Version: 2.1
Name: cloud-scanner
Version: 0.1.3
Summary: Core package for scanning cloud resources across providers
Home-page: https://microsoft.github.io/cloud-scanner
Author: Microsoft
Author-email: cloudscanner@microsoft.com
License: MIT
Platform: UNKNOWN
Requires-Dist: python-dotenv
Requires-Dist: pytest
Requires-Dist: pytest-cov
Requires-Dist: click
